Workbook

Sheet Test Cases
A1: S.No | B1: Module | C1: Spec File | D1: Line | E1: Suite (describe) | F1: Test ID | G1: Test Title | H1: Existing Tags | I1: Regression (Y/N) | J1: Smoke (Y/N) | K1: Priority | L1: New Tag(s) | M1: Remarks
A2: 1 | B2: root | C2: Pricing_general_Create.spec.js | D2: 21 | E2: Pricing_general_Create | F2: TC01 | G2: TC01 - Create a General price list with Overall Markup
A3: 2 | B3: root | C3: Pricing_general_Create.spec.js | D3: 33 | E3: Pricing_general_Create | F3: TC02 | G3: TC02 - Create a General price list with Overall Markdown
A4: 3 | B4: root | C4: Pricing_general_Create.spec.js | D4: 45 | E4: Pricing_general_Create | F4: TC03 | G4: TC03 - Create a General price list with Item Specific pricing
A5: 4 | B5: root | C5: Pricing_general_Create.spec.js | D5: 57 | E5: Pricing_general_Create | F5: TC04 | G5: TC04 - Create a General price list with Item Specific pricing by auto calculation
A6: 5 | B6: root | C6: Pricing_general_Create.spec.js | D6: 69 | E6: Pricing_general_Create | F6: TC05 | G6: TC05 - Create a Category Wise price list with Overall Markup
A7: 6 | B7: root | C7: Pricing_general_Create.spec.js | D7: 82 | E7: Pricing_general_Create | F7: TC06 | G7: TC06 - Create a Category Wise price list with Overall Markdown
A8: 7 | B8: root | C8: Pricing_general_Create.spec.js | D8: 94 | E8: Pricing_general_Create | F8: TC07 | G8: TC07 - Create a Category Wise price list with Item Specific pricing
A9: 8 | B9: root | C9: Pricing_general_Create.spec.js | D9: 106 | E9: Pricing_general_Create | F9: TC08 | G9: TC08 - Create a Category Wise price list with Item Specific pricing by auto calculation
A10: 9 | B10: root | C10: Pricing_general_Create.spec.js | D10: 118 | E10: Pricing_general_Create | F10: TC09 | G10: TC09 - Create a Profile Wise price list with Overall Markup
A11: 10 | B11: root | C11: Pricing_general_Create.spec.js | D11: 131 | E11: Pricing_general_Create | F11: TC10 | G11: TC10 - Create a Profile Wise price list with Overall Markdown
A12: 11 | B12: root | C12: Pricing_general_Create.spec.js | D12: 143 | E12: Pricing_general_Create | F12: TC11 | G12: TC11 - Create a Profile Wise price list with Item Specific pricing
A13: 12 | B13: root | C13: Pricing_general_Create.spec.js | D13: 155 | E13: Pricing_general_Create | F13: TC12 | G13: TC12 - Create a Profile Wise price list with Item Specific pricing by auto calculation
... A32: 31 | B32: root | C32: Vendor_Create.spec.js | D32: 46 | E32: Vendor_Create | F32: TC04 | G32: TC04 - Edit the Business Vendor with GST
A33: 32 | B33: _tools | C33: _tools/pricing-cleanup.spec.js | D33: 9 | G33: cleanup: no active ZZ price lists / offers
A34: 33 | B34: finance | C34: finance/01_ChequeTracker.spec.js | D34: 51 | E34: Cheque Tracker | F34: CT TC-UI-01 / 04 / 05 / 06 / 07 / 08 / 09 / 13 / 14 / 15 / 16 / 17 | G34: CT TC-UI-01 / 04 / 05 / 06 / 07 / 08 / 09 / 13 / 14 / 15 / 16 / 17 - Tabs with counts; columns per tab; Search, dates, Export, Move to (Revert on Cleared); ⋮ on rows | H34: @cheque @finance
A35: 34 | B35: finance | C35: finance/01_ChequeTracker.spec.js | D35: 79 | E35: Cheque Tracker | F35: CT TC-UI-10 / 11 | G35: CT TC-UI-10 / 11 - Header checkbox selects every row; a row checkbox selects one | H35: @cheque @finance
A36: 35 | B36: finance | C36: finance/01_ChequeTracker.spec.js | D36: 93 | E36: Cheque Tracker | F36: CT TC-CIH-01 / 02 / 12 / TC-INT-01 | G36: CT TC-CIH-01 / 02 / 12 / TC-INT-01 - Cheque payment lands in Cheque In Hand with its details; invoice stays due | H36: @cheque @finance
A37: 36 | B37: finance | C37: finance/01_ChequeTracker.spec.js | D37: 105 | E37: Cheque Tracker | F37: CT TC-CIH-03 / TC-UI-03 / TC-DEP-01 / 07 / TC-INT-02 | G37: CT TC-CIH-03 / TC-UI-03 / TC-DEP-01 / 07 / TC-INT-02 - In Hand → Deposited: counts move by one, Deposited Date today, invoice still due | H37: @cheque @finance
A38: 37 | B38: finance | C38: finance/01_ChequeTracker.spec.js | D38: 117 | E38: Cheque Tracker | F38: CT TC-DEP-02 / TC-CLR-01 / 02 / 03 / 06 / TC-INT-03 / TC-RP-24 / TC-MT-09 | G38: CT TC-DEP-02 / TC-CLR-01 / 02 / 03 / 06 / TC-INT-03 / TC-RP-24 / TC-MT-09 - Deposited → Cleared: Cleared Date today; invoice Paid | H38: @cheque @finance
A39: 38 | B39: finance | C39: finance/01_ChequeTracker.spec.js | D39: 127 | E39: Cheque Tracker | F39: CT TC-CLR-04 / TC-INT-04 / TC-EC-05 | G39: CT TC-CLR-04 / TC-INT-04 / TC-EC-05 - Revert a cleared cheque: back In Hand, invoice due again | H39: @cheque @finance
A40: 39 | B40: finance | C40: finance/01_ChequeTracker.spec.js | D40: 137 | E40: Cheque Tracker | F40: CT TC-CIH-04 / TC-CAN-01 / 06 / TC-INT-05 | G40: CT TC-CIH-04 / TC-CAN-01 / 06 / TC-INT-05 - In Hand → Cancelled: Cancelled Date today, invoice due | H40: @cheque @finance
A41: 40 | B41: finance | C41: finance/01_ChequeTracker.spec.js | D41: 144 | E41: Cheque Tracker | F41: CT TC-CAN-02 / 03 / 04 / 05 | G41: CT TC-CAN-02 / 03 / 04 / 05 - Cancelled → In Hand / Deposited / Returned allowed; Cleared not offered | H41: @cheque @finance
A42: 41 | B42: finance | C42: finance/01_ChequeTracker.spec.js | D42: 160 | E42: Cheque Tracker | F42: CT TC-CIH-05 / TC-RET-01 / 02 / 13 / TC-INT-06 | G42: CT TC-CIH-05 / TC-RET-01 / 02 / 13 / TC-INT-06 - In Hand → Returned: Returned Date, Late Fee Charge filled; invoice due | H42: @cheque @finance
A43: 42 | B43: finance | C43: finance/01_ChequeTracker.spec.js | D43: 169 | E43: Cheque Tracker | F43: CT TC-CIH-06 / TC-DEP-05 / TC-MT-03 | G43: CT TC-CIH-06 / TC-DEP-05 / TC-MT-03 - Bulk: three cheques In Hand → Deposited → Cleared together | H43: @cheque @finance
A44: 43 | B44: finance | C44: finance/01_ChequeTracker.spec.js | D44: 181 | E44: Cheque Tracker | F44: CT TC-CIH-07 / TC-DEP-06 / TC-MT-05 / 07 / TC-EC-07 | G44: CT TC-CIH-07 / TC-DEP-06 / TC-MT-05 / 07 / TC-EC-07 - A future-dated cheque cannot be moved; today's can (mixed bulk moves only the dated one) | H44: @cheque @finance
A45: 44 | B45: finance | C45: finance/01_ChequeTracker.spec.js | D45: 190 | E45: Cheque Tracker | F45: CT TC-CIH-08 / TC-MT-06 | G45: CT TC-CIH-08 / TC-MT-06 - Move to with nothing selected does nothing (or asks to select) | H45: @cheque @finance
... A55: 54 | B55: finance | C55: finance/01_ChequeTracker.spec.js | D55: 325 | E55: Cheque Tracker | F55: CT TC-RET-11 / TC-EC-04 | G55: CT TC-RET-11 / TC-EC-04 - A returned cheque without a collected fee can be deleted (⋮ Delete) | H55: @cheque @finance
A56: 55 | B56: finance | C56: finance/01_ChequeTracker.spec.js | D56: 346 | E56: Cheque Tracker | F56: CT TC-UI-02 | G56: CT TC-UI-02 - Tab counts = records (Counts are checked as they change (CT TC-CIH-03); other users add cheques to the same org.)
A57: 56 | B57: finance | C57: finance/01_ChequeTracker.spec.js | D57: 346 | E57: Cheque Tracker | F57: CT TC-UI-12 | G57: CT TC-UI-12 - Responsive layout (Visual design check.)
A58: 57 | B58: finance | C58: finance/01_ChequeTracker.spec.js | D58: 346 | E58: Cheque Tracker | F58: CT TC-CIH-10 / 11 | G58: CT TC-CIH-10 / 11 - Upload attachment (image / invalid file) (Needs image fixtures for the upload dialog.)
A59: 58 | B59: finance | C59: finance/01_ChequeTracker.spec.js | D59: 346 | E59: Cheque Tracker | F59: CT TC-CLR-05 | G59: CT TC-CLR-05 - Bulk revert (Same Revert action as CT TC-CLR-04, run per cheque.)
A60: 59 | B60: finance | C60: finance/01_ChequeTracker.spec.js | D60: 346 | E60: Cheque Tracker | F60: CT TC-CLR-07 / TC-CAN-07 / TC-RET-14 | G60: CT TC-CLR-07 / TC-CAN-07 / TC-RET-14 - Future-dated cheque on later tabs (A future-dated cheque cannot leave In Hand (CT TC-CIH-07), so it never reaches these tabs.)
A61: 60 | B61: finance | C61: finance/01_ChequeTracker.spec.js | D61: 346 | E61: Cheque Tracker | F61: CT TC-RET-12 / TC-INT-07 / 08 / 09 | G61: CT TC-RET-12 / TC-INT-07 / 08 / 09 - Customer Transaction report entries (Customer statement checks belong to the Customer_Transaction sheet; invoice status is checked here.)
A62: 61 | B62: finance | C62: finance/01_ChequeTracker.spec.js | D62: 346 | E62: Cheque Tracker | F62: CT TC-EXP-03 | G62: CT TC-EXP-03 - Returned export columns (Export file content needs a spreadsheet parser.)
A63: 62 | B63: finance | C63: finance/01_ChequeTracker.spec.js | D63: 346 | E63: Cheque Tracker | F63: CT TC-EC-06 | G63: CT TC-EC-06 - Bulk with a cleared + an in-hand cheque (Cheques of different tabs cannot be selected together (one tab at a time).)
A64: 63 | B64: finance | C64: finance/02_ManualJournal.spec.js | D64: 43 | E64: Manual Journal | F64: MJ TC-UI-01 / 06 / 07 / 08 / TC-CJ-01 / 02 / 09 / TC-UI-02 | G64: MJ TC-UI-01 / 06 / 07 / 08 / TC-CJ-01 / 02 / 09 / TC-UI-02 - List columns and Total Count; Finance tabs; New Journal: MJN-AUTO no (read-only), today, Accrual Only default, rows and totals | H64: @finance @mj
A65: 64 | B65: finance | C65: finance/02_ManualJournal.spec.js | D65: 60 | E65: Manual Journal | F65: MJ TC-CJ-07 / TC-LI-03 | G65: MJ TC-CJ-07 / TC-LI-03 - Notes required ("Notes is Required!"); no amounts refused | H65: @finance @mj
A66: 65 | B66: finance | C66: finance/02_ManualJournal.spec.js | D66: 73 | E66: Manual Journal | F66: MJ TC-CJ-08 / 05 / TC-LI-01 / 04 / 05 / 10 / 16 / 17 / 18 / TC-WF-03 / TC-UI-03 / 04 / 05 / TC-DI-02 / 05 | G66: MJ TC-CJ-08 / 05 / TC-LI-01 / 04 / 05 / 10 / 16 / 17 / 18 / TC-WF-03 / TC-UI-03 / 04 / 05 / TC-DI-02 / 05 - Balanced ₹100 (no reference / description / contact): Open, amount 100, notes in list; view with Print / Edit / Delete | H66: @finance @mj
A67: 66 | B67: finance | C67: finance/02_ManualJournal.spec.js | D67: 92 | E67: Manual Journal | F67: MJ TC-CJ-03 / 04 / 06 | G67: MJ TC-CJ-03 / 04 / 06 - Past and future dates and an alphanumeric reference are accepted | H67: @finance @mj
A68: 67 | B68: finance | C68: finance/02_ManualJournal.spec.js | D68: 104 | E68: Manual Journal | F68: MJ TC-LI-11 / 12 / TC-WF-10 | G68: MJ TC-LI-11 / 12 / TC-WF-10 - Unbalanced (100 / 80) and debit-only journals are refused; Difference shown | H68: @finance @mj
A69: 68 | B69: finance | C69: finance/02_ManualJournal.spec.js | D69: 115 | E69: Manual Journal | F69: MJ TC-LI-06 / 07 / 08 / 09 | G69: MJ TC-LI-06 / 07 / 08 / 09 - Debit and credit on one line refused; 0 and "-" refused; decimals 354.50 balance | H69: @finance @mj
A70: 69 | B70: finance | C70: finance/02_ManualJournal.spec.js | D70: 129 | E70: Manual Journal | F70: MJ TC-LI-02 / 14 / 15 / 19 | G70: MJ TC-LI-02 / 14 / 15 / 19 - Three debits (100 + 200 + 300) and two credits (250 + 350): sub totals 600, saved | H70: @finance @mj
A71: 70 | B71: finance | C71: finance/02_ManualJournal.spec.js | D71: 144 | E71: Manual Journal | F71: MJ TC-JT-01 / 10 / TC-CT-01 | G71: MJ TC-JT-01 / 10 / TC-CT-01 - Accrual Only with Accounts Receivable + contact saves; the customer due moves by the amount | H71: @finance @mj
A72: 71 | B72: finance | C72: finance/02_ManualJournal.spec.js | D72: 156 | E72: Manual Journal | F72: MJ TC-JT-02 / TC-CT-02 | G72: MJ TC-JT-02 / TC-CT-02 - Accrual Only with Accounts Payable + vendor contact saves | H72: @finance @mj
A73: 72 | B73: finance | C73: finance/02_ManualJournal.spec.js | D73: 162 | E73: Manual Journal | F73: MJ TC-JT-03 / 08 / 09 | G73: MJ TC-JT-03 / 08 / 09 - Cash Only with Accounts Receivable is refused; switching the account to Petty Cash then saves | H73: @finance @mj
A74: 73 | B74: finance | C74: finance/02_ManualJournal.spec.js | D74: 173 | E74: Manual Journal | F74: MJ TC-CJ-10 / 11 / TC-JT-07 | G74: MJ TC-CJ-10 / 11 / TC-JT-07 - Cash Only and Accrual and Cash journals with non-A/R accounts save | H74: @finance @mj
A75: 74 | B75: finance | C75: finance/02_ManualJournal.spec.js | D75: 183 | E75: Manual Journal | F75: MJ TC-WF-02 | G75: MJ TC-WF-02 - An unbalanced journal can be saved as Draft | H75: @finance @mj
... A85: 84 | B85: finance | C85: finance/02_ManualJournal.spec.js | D85: 338 | E85: Manual Journal | F85: MJ TC-INT-09 | G85: MJ TC-INT-09 - A returned cheque without a collected fee creates no journal | H85: @finance @mj
A86: 85 | B86: finance | C86: finance/02_ManualJournal.spec.js | D86: 354 | E86: Manual Journal | F86: MJ TC-PG-02 / 03 / 10 | G86: MJ TC-PG-02 / 03 / 10 - Page size 50 / 100 (The journal list has fewer than 50 entries.)
A87: 86 | B87: finance | C87: finance/02_ManualJournal.spec.js | D87: 354 | E87: Manual Journal | F87: MJ TC-COA-01 … 05 | G87: MJ TC-COA-01 … 05 - Chart of Accounts balances (No Chart of Accounts screen in the Finance menu of this build.)
A88: 87 | B88: finance | C88: finance/02_ManualJournal.spec.js | D88: 354 | E88: Manual Journal | F88: MJ TC-CT-03 / 04 | G88: MJ TC-CT-03 / 04 - Customer statement after delete / for drafts (Customer balance is checked on create (MJ TC-CT-01).)
A89: 88 | B89: finance | C89: finance/02_ManualJournal.spec.js | D89: 354 | E89: Manual Journal | F89: MJ TC-INT-07 / 08 / 10 / 11 / 12 / TC-DI-08 | G89: MJ TC-INT-07 / 08 / 10 / 11 / 12 / TC-DI-08 - Several / partial late fees, statement entry, deleting the late-fee journal (One late-fee journal is checked (MJ TC-INT-01); partial collection is a Cheque Tracker case.)
A90: 89 | B90: inventory | C90: inventory/02_InventoryProduct.spec.js | D90: 53 | E90: Inventory Product | F90: INV_FUNC_001 / INV_UI_001 / 005 / 006 / 013 / 014 | G90: INV_FUNC_001 / INV_UI_001 / 005 / 006 / 013 / 014 - Tabs Items / Asset / Service / Category; list columns and Total Count per tab | H90: @inv @inventory
A91: 90 | B91: inventory | C91: inventory/02_InventoryProduct.spec.js | D91: 72 | E91: Inventory Product | F91: INV_FUNC_002 / 003 / 004 / INV_UI_003 / 012 | G91: INV_FUNC_002 / 003 / 004 / INV_UI_003 / 012 - Item form (one drawer, adapted from 3 steps): Basic Info, Sale Details, Purchase Details fields | H91: @inv @inventory
A92: 91 | B92: inventory | C92: inventory/02_InventoryProduct.spec.js | D92: 80 | E92: Inventory Product | F92: INV_NEG_001 / INV_VAL_001 / 006 / INV_UI_004 | G92: INV_NEG_001 / INV_VAL_001 / 006 / INV_UI_004 - Save empty: Name, Selling Price, Tax Preference and GST required | H92: @inv @inventory
A93: 92 | B93: inventory | C93: inventory/02_InventoryProduct.spec.js | D93: 89 | E93: Inventory Product | F93: INV_FUNC_007 / INV_POS_001 / 003 / 007 / INV_BND_002 / 006 / INV_BL_002 / INV_E2E_001 / 013 / INV_UI_002 | G93: INV_FUNC_007 / INV_POS_001 / 003 / 007 / INV_BND_002 / 006 / INV_BL_002 / INV_E2E_001 / 013 / INV_UI_002 - Item with 8-digit HSN, GST12, ₹250: listed with HSN, 12%, ₹250 and Out of stocks (no stock) | H93: @inv @inventory
A94: 93 | B94: inventory | C94: inventory/02_InventoryProduct.spec.js | D94: 100 | E94: Inventory Product | F94: INV_FUNC_008 / INV_E2E_006 | G94: INV_FUNC_008 / INV_E2E_006 - Close on a filled item form creates nothing | H94: @inv @inventory
A95: 94 | B95: inventory | C95: inventory/02_InventoryProduct.spec.js | D95: 109 | E95: Inventory Product | F95: INV_NEG_003 / INV_VAL_002 / 003 / INV_BND_003 / 004 | G95: INV_NEG_003 / INV_VAL_002 / 003 / INV_BND_003 / 004 - HSN: 7 digits refused; letters and a 9th digit not accepted | H95: @inv @inventory
A96: 95 | B96: inventory | C96: inventory/02_InventoryProduct.spec.js | D96: 120 | E96: Inventory Product | F96: INV_NEG_004 / 011 / INV_VAL_007 | G96: INV_NEG_004 / 011 / INV_VAL_007 - Sale price: "-" and letters refused | H96: @inv @inventory
A97: 96 | B97: inventory | C97: inventory/02_InventoryProduct.spec.js | D97: 130 | E97: Inventory Product | F97: INV_NEG_016 / INV_VAL_012 | G97: INV_NEG_016 / INV_VAL_012 - Cost per pcs: "-" refused | H97: @inv @inventory
A98: 97 | B98: inventory | C98: inventory/02_InventoryProduct.spec.js | D98: 138 | E98: Inventory Product | F98: INV_BND_001 / 008 / INV_VAL_013 | G98: INV_BND_001 / 008 / INV_VAL_013 - One-character name and ₹0.01 save; a 300-character name is limited or refused | H98: @inv @inventory
A99: 98 | B99: inventory | C99: inventory/02_InventoryProduct.spec.js | D99: 158 | E99: Inventory Product | F99: INV_NEG_014 / INV_VAL_018 | G99: INV_NEG_014 / INV_VAL_018 - A second item with the same name is refused or warned about | H99: @inv @inventory
A100: 99 | B100: inventory | C100: inventory/02_InventoryProduct.spec.js | D100: 168 | E100: Inventory Product | F100: INV_NEG_018 / INV_SEC_005 | G100: INV_NEG_018 / INV_SEC_005 - Script text in the product name is not run | H100: @inv @inventory
A101: 100 | B101: inventory | C101: inventory/02_InventoryProduct.spec.js | D101: 181 | E101: Inventory Product | F101: INV_POS_014 / INV_VAL_014 | G101: INV_POS_014 / INV_VAL_014 - CESS rate 5 % saved and shown in Tax Preferences | H101: @inv @inventory
... A117: 116 | B117: inventory | C117: inventory/02_InventoryProduct.spec.js | D117: 426 | E117: Inventory Product | F117: INV_SEC_001 / 011 | G117: INV_SEC_001 / 011 - Without a session the products page redirects to login | H117: @inv @inventory
A118: 117 | B118: inventory | C118: inventory/02_InventoryProduct.spec.js | D118: 461 | E118: Inventory Product | F118: INV_FUNC_005 / 006 / INV_UI_003 (steps) | G118: INV_FUNC_005 / 006 / INV_UI_003 (steps) - Wizard Back / Next between steps (The item form is one drawer — no steps.)
A119: 118 | B119: inventory | C119: inventory/02_InventoryProduct.spec.js | D119: 461 | E119: Inventory Product | F119: INV_NEG_002 / INV_VAL_005 | G119: INV_NEG_002 / INV_VAL_005 - Unit of Measure required (Unit of Measure defaults to pcs (Nos for services) and cannot be emptied.)
A120: 119 | B120: inventory | C120: inventory/02_InventoryProduct.spec.js | D120: 461 | E120: Inventory Product | F120: INV_NEG_005 / 012 / INV_VAL_010 / INV_BND_009 / INV_BL_001 | G120: INV_NEG_005 / 012 / INV_VAL_010 / INV_BND_009 / INV_BL_001 - Opening stock on the item form (No opening-stock field — stock comes from a stock adjustment (shared setupItem).)
A121: 120 | B121: inventory | C121: inventory/02_InventoryProduct.spec.js | D121: 461 | E121: Inventory Product | F121: INV_NEG_015 / INV_VAL_011 / INV_FUNC_015 / INV_POS_016 / INV_BL_010 / INV_BND_011 | G121: INV_NEG_015 / INV_VAL_011 / INV_FUNC_015 / INV_POS_016 / INV_BL_010 / INV_BND_011 - Minimum stock reminder (No minimum-stock field on the item form or detail.)
A122: 121 | B122: inventory | C122: inventory/02_InventoryProduct.spec.js | D122: 461 | E122: Inventory Product | F122: INV_POS_004 / INV_BL_009 | G122: INV_POS_004 / INV_BL_009 - Batch tracking (Stock Tracking options need batch-enabled warehouses — not in this org.)
A123: 122 | B123: inventory | C123: inventory/02_InventoryProduct.spec.js | D123: 461 | E123: Inventory Product | F123: INV_VAL_017 | G123: INV_VAL_017 - Out-of-stock item cannot be sold (Sales allow negative stock in this org (TC-ST checks).)
A124: 123 | B124: inventory | C124: inventory/02_InventoryProduct.spec.js | D124: 461 | E124: Inventory Product | F124: INV_VAL_016 | G124: INV_VAL_016 - Inactive service on sales invoice (Same switch as items — checked for items (INV_FUNC_011).)
A125: 124 | B125: inventory | C125: inventory/02_InventoryProduct.spec.js | D125: 461 | E125: Inventory Product | F125: INV_VAL_019 | G125: INV_VAL_019 - Circular parent category (Parent list only offers existing categories; a child cannot be picked for its own parent without a second edit flow.)
A126: 125 | B126: inventory | C126: inventory/02_InventoryProduct.spec.js | D126: 461 | E126: Inventory Product | F126: INV_VAL_020 / INV_BND_012 | G126: INV_VAL_020 / INV_BND_012 - Alternate UOM conversion 0 / 1 (Alternate UOMs are covered by the Sales Invoice stock sheet.)
A127: 126 | B127: inventory | C127: inventory/02_InventoryProduct.spec.js | D127: 461 | E127: Inventory Product | F127: INV_BL_014 / 015 / 017 / 018 | G127: INV_BL_014 / 015 / 017 / 018 - Journal accounts / CESS on invoices (Covered by the Sales / Purchase invoice journal and CESS tests.)
A128: 127 | B128: inventory | C128: inventory/02_InventoryProduct.spec.js | D128: 461 | E128: Inventory Product | F128: INV_PAG_001…004 / 006 / 010 | G128: INV_PAG_001…004 / 006 / 010 - Category / service pagination, exactly 20 items (The org has < 20 categories / services; exact counts need a controlled org.)
A129: 128 | B129: inventory | C129: inventory/02_InventoryProduct.spec.js | D129: 461 | E129: Inventory Product | F129: INV_SF_009 | G129: INV_SF_009 - Search by HSN code (Search is by name only (checked: name search).)
... A138: 137 | B138: inventory | C138: inventory/02_InventoryProduct.spec.js | D138: 461 | E138: Inventory Product | F138: INV_ACC_001 / 002 / 003 / 004 / 005 / 007 / 008 | G138: INV_ACC_001 / 002 / 003 / 004 / 005 / 007 / 008 - Keyboard list, screen reader, contrast, labels (Needs an accessibility audit tool (axe) / screen reader.)
A139: 138 | B139: inventory | C139: inventory/03_PriceList.spec.js | D139: 51 | E139: Price List | F139: PL_FUNC_001 / PL_UI_001 / PL_UI_002 / PL_POS_015 | G139: PL_FUNC_001 / PL_UI_001 / PL_UI_002 / PL_POS_015 - List: Price List Name, List Type, Pricing, Status, No Of Items; Active badge text; Total Count | H139: @inventory @pricelist
A140: 139 | B140: inventory | C140: inventory/03_PriceList.spec.js | D140: 59 | E140: Price List | F140: PL_FUNC_002 / 003 / 004 / 005 / 006 / 007 / PL_UI_003 / 004 / 005 / 013 | G140: PL_FUNC_002 / 003 / 004 / 005 / 006 / 007 / PL_UI_003 / 004 / 005 / 013 - Form: name, description, type General / Profile wise / Category wise (profiles; business type & category), Overall Markup (Markup|Markdown + rate) / Item Specific (item list) | H140: @inventory @pricelist
A141: 140 | B141: inventory | C141: inventory/03_PriceList.spec.js | D141: 77 | E141: Price List | F141: PL_NEG_001 / 006 / 003 | G141: PL_NEG_001 / 006 / 003 - Empty save: Name and Custom Rate required; the rate refuses letters and "-" | H141: @inventory @pricelist
A142: 141 | B142: inventory | C142: inventory/03_PriceList.spec.js | D142: 91 | E142: Price List | F142: PL_NEG_002 | G142: PL_NEG_002 - Custom rate 0 % is refused | H142: @inventory @pricelist
A143: 142 | B143: inventory | C143: inventory/03_PriceList.spec.js | D143: 101 | E143: Price List | F143: PL_NEG_016 | G143: PL_NEG_016 - Custom rate above 1000 % is refused or warned about | H143: @inventory @pricelist
A144: 143 | B144: inventory | C144: inventory/03_PriceList.spec.js | D144: 111 | E144: Price List | F144: PL_POS_006 / 007 / PL_UI_009 / PL_NEG_010 | G144: PL_POS_006 / 007 / PL_UI_009 / PL_NEG_010 - Description: counter "N / 300", limited to 300; Remove collapses it | H144: @inventory @pricelist
A145: 144 | B145: inventory | C145: inventory/03_PriceList.spec.js | D145: 127 | E145: Price List | F145: PL_VAL_012 / PL_BND_011 | G145: PL_VAL_012 / PL_BND_011 - Whitespace-only name refused; a 1-character name saves | H145: @inventory @pricelist
A146: 145 | B146: inventory | C146: inventory/03_PriceList.spec.js | D146: 141 | E146: Price List | F146: PL_VAL_015 | G146: PL_VAL_015 - A second list with the same name is refused or warned about | H146: @inventory @pricelist
A147: 146 | B147: inventory | C147: inventory/03_PriceList.spec.js | D147: 150 | E147: Price List | F147: PL_NEG_013 / PL_SEC_005 / 006 | G147: PL_NEG_013 / PL_SEC_005 / 006 - Script text in name / description is not run | H147: @inventory @pricelist
A148: 147 | B148: inventory | C148: inventory/03_PriceList.spec.js | D148: 162 | E148: Price List | F148: PL_FUNC_008 / 012 / PL_POS_001 / 009 / 014 / 018 / PL_UI_007 / PL_BL_001 / 002 / 014 / PL_E2E_001 / 010 / TC-27 | G148: PL_FUNC_008 / 012 / PL_POS_001 / 009 / 014 / 018 / PL_UI_007 / PL_BL_001 / 002 / 014 / PL_E2E_001 / 010 / TC-27 - General Markup 10 %: list (General, Markup 10 %, Active, All Items), view, ₹100 item → ₹110 on the invoice | H148: @inventory @pricelist
A149: 148 | B149: inventory | C149: inventory/03_PriceList.spec.js | D149: 174 | E149: Price List | F149: PL_POS_002 / PL_BL_003 / 015 / PL_E2E_002 / PL_BND_012 / TC-28 | G149: PL_POS_002 / PL_BL_003 / 015 / PL_E2E_002 / PL_BND_012 / TC-28 - Markdown 10 % → ₹90; Markdown 34 % → ₹66; Markup 10.5 % → ₹110.5 | H149: @inventory @pricelist
A150: 149 | B150: inventory | C150: inventory/03_PriceList.spec.js | D150: 183 | E150: Price List | F150: PL_BND_002 / 003 / 001 / PL_POS_016 / PL_BL_017 | G150: PL_BND_002 / 003 / 001 / PL_POS_016 / PL_BL_017 - Markup 100 % doubles; Markdown 100 % → ₹0 (or refused); 0.01 % saves | H150: @inventory @pricelist
... A161: 160 | B161: inventory | C161: inventory/03_PriceList.spec.js | D161: 326 | E161: Price List | F161: PL_SEC_001 / 010 | G161: PL_SEC_001 / 010 - Without a session the pricing page redirects to login; URLs hold no rates | H161: @inventory @pricelist
A162: 161 | B162: inventory | C162: inventory/03_PriceList.spec.js | D162: 358 | E162: Price List | F162: PL_FUNC_019 / 020 | G162: PL_FUNC_019 / 020 - Several profile tags / remove a tag (Covered by one profile (PL_FUNC_009); tag removal needs a second spare customer.)
A163: 162 | B163: inventory | C163: inventory/03_PriceList.spec.js | D163: 358 | E163: Price List | F163: PL_FUNC_021 / 022 / PL_UI_006 / PL_VAL_010 / 013 / 016 / PL_BL_008 / 012 / 020 / PL_POS_012 / PL_E2E_006 / 014 | G163: PL_FUNC_021 / 022 / PL_UI_006 / PL_VAL_010 / 013 / 016 / PL_BL_008 / 012 / 020 / PL_POS_012 / PL_E2E_006 / 014 - Auto Calculate / additional UOM prices (Needs an item with alternate UOMs in an Item Specific list — UOM pricing is covered by the Sales Invoice stock sheet.)
A164: 163 | B164: inventory | C164: inventory/03_PriceList.spec.js | D164: 358 | E164: Price List | F164: PL_POS_008 / 013 / PL_BL_018 | G164: PL_POS_008 / 013 / PL_BL_018 - Beat Routes (No Beat Routes field in this build.)
A165: 164 | B165: inventory | C165: inventory/03_PriceList.spec.js | D165: 358 | E165: Price List | F165: PL_POS_010 | G165: PL_POS_010 - Switch Overall Markup → Item Specific on edit (Same form as create (both modes checked).)
A166: 165 | B166: inventory | C166: inventory/03_PriceList.spec.js | D166: 358 | E166: Price List | F166: PL_POS_017 / PL_UI_010 / PL_SF_007…010 | G166: PL_POS_017 / PL_UI_010 / PL_SF_007…010 - Item search inside the view (Needs an Item Specific list with many items.)
A167: 166 | B167: inventory | C167: inventory/03_PriceList.spec.js | D167: 358 | E167: Price List | F167: PL_NEG_007 / 008 / PL_BND_009 / 010 | G167: PL_NEG_007 / 008 / PL_BND_009 / 010 - Item Specific price 0 / negative / 0.01 / 99.99 (Item price field rules follow the custom rate field (PL_NEG_006).)
A168: 167 | B168: inventory | C168: inventory/03_PriceList.spec.js | D168: 358 | E168: Price List | F168: PL_NEG_012 / PL_VAL_005 / PL_VAL_019 / PL_BL_005 / 006 / PL_E2E_004 | G168: PL_NEG_012 / PL_VAL_005 / PL_VAL_019 / PL_BL_005 / 006 / PL_E2E_004 - Category wise without business type / per-category pricing on invoices (Business Type defaults to Retailer; customers with controlled business type / category are needed.)
A169: 168 | B169: inventory | C169: inventory/03_PriceList.spec.js | D169: 358 | E169: Price List | F169: PL_BL_011 | G169: PL_BL_011 - Priority between several active lists (The org has 380 lists from other runs; priority needs a clean org.)
...

Sheet Summary
A1: Spec File | B1: Total Tests | C1: Regression = Y | D1: Smoke = Y | E1: Not yet marked
A2: Pricing_general_Create.spec.js | B2: =COUNTIF('Test Cases'!$C$2:$C$967,A2) -> 26 | C2: =COUNTIFS('Test Cases'!$C$2:$C$967,A2,'Test Cases'!$I$2:$I$967,"Y") -> 0 | D2: =COUNTIFS('Test Cases'!$C$2:$C$967,A2,'Test Cases'!$J$2:$J$967,"Y") -> 0 | E2: =COUNTIFS('Test Cases'!$C$2:$C$967,A2,'Test Cases'!$I$2:$I$967,"") -> 26
A3: Product_item_Create.spec.js | B3: =COUNTIF('Test Cases'!$C$2:$C$967,A3) -> 1 | C3: =COUNTIFS('Test Cases'!$C$2:$C$967,A3,'Test Cases'!$I$2:$I$967,"Y") -> 0 | D3: =COUNTIFS('Test Cases'!$C$2:$C$967,A3,'Test Cases'!$J$2:$J$967,"Y") -> 0 | E3: =COUNTIFS('Test Cases'!$C$2:$C$967,A3,'Test Cases'!$I$2:$I$967,"") -> 1
A4: Vendor_Create.spec.js | B4: =COUNTIF('Test Cases'!$C$2:$C$967,A4) -> 4 | C4: =COUNTIFS('Test Cases'!$C$2:$C$967,A4,'Test Cases'!$I$2:$I$967,"Y") -> 0 | D4: =COUNTIFS('Test Cases'!$C$2:$C$967,A4,'Test Cases'!$J$2:$J$967,"Y") -> 0 | E4: =COUNTIFS('Test Cases'!$C$2:$C$967,A4,'Test Cases'!$I$2:$I$967,"") -> 4
A5: _tools/pricing-cleanup.spec.js | B5: =COUNTIF('Test Cases'!$C$2:$C$967,A5) -> 1 | C5: =COUNTIFS('Test Cases'!$C$2:$C$967,A5,'Test Cases'!$I$2:$I$967,"Y") -> 0 | D5: =COUNTIFS('Test Cases'!$C$2:$C$967,A5,'Test Cases'!$J$2:$J$967,"Y") -> 0 | E5: =COUNTIFS('Test Cases'!$C$2:$C$967,A5,'Test Cases'!$I$2:$I$967,"") -> 1
A6: finance/01_ChequeTracker.spec.js | B6: =COUNTIF('Test Cases'!$C$2:$C$967,A6) -> 30 | C6: =COUNTIFS('Test Cases'!$C$2:$C$967,A6,'Test Cases'!$I$2:$I$967,"Y") -> 0 | D6: =COUNTIFS('Test Cases'!$C$2:$C$967,A6,'Test Cases'!$J$2:$J$967,"Y") -> 0 | E6: =COUNTIFS('Test Cases'!$C$2:$C$967,A6,'Test Cases'!$I$2:$I$967,"") -> 30
A7: finance/02_ManualJournal.spec.js | B7: =COUNTIF('Test Cases'!$C$2:$C$967,A7) -> 26 | C7: =COUNTIFS('Test Cases'!$C$2:$C$967,A7,'Test Cases'!$I$2:$I$967,"Y") -> 0 | D7: =COUNTIFS('Test Cases'!$C$2:$C$967,A7,'Test Cases'!$J$2:$J$967,"Y") -> 0 | E7: =COUNTIFS('Test Cases'!$C$2:$C$967,A7,'Test Cases'!$I$2:$I$967,"") -> 26
A8: inventory/02_InventoryProduct.spec.js | B8: =COUNTIF('Test Cases'!$C$2:$C$967,A8) -> 49 | C8: =COUNTIFS('Test Cases'!$C$2:$C$967,A8,'Test Cases'!$I$2:$I$967,"Y") -> 0 | D8: =COUNTIFS('Test Cases'!$C$2:$C$967,A8,'Test Cases'!$J$2:$J$967,"Y") -> 0 | E8: =COUNTIFS('Test Cases'!$C$2:$C$967,A8,'Test Cases'!$I$2:$I$967,"") -> 49
A9: inventory/03_PriceList.spec.js | B9: =COUNTIF('Test Cases'!$C$2:$C$967,A9) -> 40 | C9: =COUNTIFS('Test Cases'!$C$2:$C$967,A9,'Test Cases'!$I$2:$I$967,"Y") -> 0 | D9: =COUNTIFS('Test Cases'!$C$2:$C$967,A9,'Test Cases'!$J$2:$J$967,"Y") -> 0 | E9: =COUNTIFS('Test Cases'!$C$2:$C$967,A9,'Test Cases'!$I$2:$I$967,"") -> 40
A10: inventory/04_Offers.spec.js | B10: =COUNTIF('Test Cases'!$C$2:$C$967,A10) -> 31 | C10: =COUNTIFS('Test Cases'!$C$2:$C$967,A10,'Test Cases'!$I$2:$I$967,"Y") -> 0 | D10: =COUNTIFS('Test Cases'!$C$2:$C$967,A10,'Test Cases'!$J$2:$J$967,"Y") -> 0 | E10: =COUNTIFS('Test Cases'!$C$2:$C$967,A10,'Test Cases'!$I$2:$I$967,"") -> 31
A11: inventory/05_VanSales.spec.js | B11: =COUNTIF('Test Cases'!$C$2:$C$967,A11) -> 11 | C11: =COUNTIFS('Test Cases'!$C$2:$C$967,A11,'Test Cases'!$I$2:$I$967,"Y") -> 0 | D11: =COUNTIFS('Test Cases'!$C$2:$C$967,A11,'Test Cases'!$J$2:$J$967,"Y") -> 0 | E11: =COUNTIFS('Test Cases'!$C$2:$C$967,A11,'Test Cases'!$I$2:$I$967,"") -> 11
A12: payment/01_CustomerPayment.spec.js | B12: =COUNTIF('Test Cases'!$C$2:$C$967,A12) -> 2 | C12: =COUNTIFS('Test Cases'!$C$2:$C$967,A12,'Test Cases'!$I$2:$I$967,"Y") -> 0 | D12: =COUNTIFS('Test Cases'!$C$2:$C$967,A12,'Test Cases'!$J$2:$J$967,"Y") -> 0 | E12: =COUNTIFS('Test Cases'!$C$2:$C$967,A12,'Test Cases'!$I$2:$I$967,"") -> 2
A13: purchase/01_PurchaseFlow.spec.js | B13: =COUNTIF('Test Cases'!$C$2:$C$967,A13) -> 14 | C13: =COUNTIFS('Test Cases'!$C$2:$C$967,A13,'Test Cases'!$I$2:$I$967,"Y") -> 0 | D13: =COUNTIFS('Test Cases'!$C$2:$C$967,A13,'Test Cases'!$J$2:$J$967,"Y") -> 0 | E13: =COUNTIFS('Test Cases'!$C$2:$C$967,A13,'Test Cases'!$I$2:$I$967,"") -> 14
... A24: unit_flows/Sales_Unit.spec.js | B24: =COUNTIF('Test Cases'!$C$2:$C$967,A24) -> 21 | C24: =COUNTIFS('Test Cases'!$C$2:$C$967,A24,'Test Cases'!$I$2:$I$967,"Y") -> 0 | D24: =COUNTIFS('Test Cases'!$C$2:$C$967,A24,'Test Cases'!$J$2:$J$967,"Y") -> 0 | E24: =COUNTIFS('Test Cases'!$C$2:$C$967,A24,'Test Cases'!$I$2:$I$967,"") -> 21
A25: TOTAL | B25: =SUM(B2:B24) -> 966 | C25: =SUM(C2:C24) -> 0 | D25: =SUM(D2:D24) -> 0 | E25: =SUM(E2:E24) -> 966
